[
  {
    "label": "Suspend",
    "exec": "systemctl suspend",
    "icon": "/home/coco/.config/nwg-bar/img/system-suspend.svg"
  },
  {
    "label": "Lock",
    "exec": "swaylock -f -c 000000",
    "icon": "/home/coco/.config/nwg-bar/img/system-lock-screen.svg"
  },
  {
    "label": "Logout",
    "exec": "pkill niri",
    "icon": "/home/coco/.config/nwg-bar/img/system-log-out.svg"
  },
  {
    "label": "Reboot",
    "exec": "systemctl reboot",
    "icon": "/home/coco/.config/nwg-bar/img/system-reboot.svg"
  },
  {
    "label": "Shutdown",
    "exec": "systemctl -i poweroff",
    "icon": "/home/coco/.config/nwg-bar/img/system-shutdown.svg"
  }
]
